terraware_devices/__init__.py
terraware_devices/base.py
terraware_devices/blue_maestro_device.py
terraware_devices/device_manager.py
terraware_devices/modbus_device.py
terraware_devices/relay_device.py
terraware_devices-0.1.7.dist-info/LICENSE.txt
terraware_devices-0.1.7.dist-info/METADATA
terraware_devices-0.1.7.dist-info/WHEEL
terraware_devices-0.1.7.dist-info/top_level.txt
terraware_devices-0.1.7.dist-info/RECORD
