Metadata-Version: 2.1
Name: terraware-devices
Version: 0.1.7
Summary: Device management for Terraformation hardware systems
Home-page: https://github.com/terraware/terraware-devices
Author: Terraformation
License: MIT
Platform: UNKNOWN
Classifier: Development Status :: 3 - Alpha
Classifier: Intended Audience :: Developers
Classifier: License :: OSI Approved :: MIT License
Classifier: Natural Language :: English
Classifier: Programming Language :: Python :: 3
Classifier: Programming Language :: Python :: 3 :: Only
Classifier: Programming Language :: Python :: 3.7
Classifier: Programming Language :: Python :: 3.8
Classifier: Programming Language :: Python :: 3.9
Requires-Python: >=3.7, <4
Requires-Dist: gevent (>=20.9)
Requires-Dist: pymodbus (~=2.4)
Requires-Dist: requests (>=2.0)
Requires-Dist: rhizo-client (~=0.1.3)
Requires-Dist: bluepy (~=1.3) ; platform_system == "Linux"
